kcf_tools/__init__.py
kcf_tools/cli.py
kcf_tools/generate/__init__.py
kcf_tools/generate/client/__init__.py
kcf_tools/generate/client/main.py
kcf_tools/generate/config_schema/__init__.py
kcf_tools/generate/config_schema/main.py
kcf_tools/generate/docs/__init__.py
kcf_tools/generate/docs/cli_help_doc.py
kcf_tools/generate/docs/doc_generator.py
kcf_tools/generate/docs/main.py
kcf_tools/generate/docs/templates/__init__.py
kcf_tools/generate/docs/templates/help_doc_template.md
kcf_tools/generate/docs/templates/help_doc_template.py
kcf_tools/generate/key_definitions/__init__.py
kcf_tools/generate/key_definitions/main.py
kcf_tools/generate/readme/__init__.py
kcf_tools/generate/readme/main.py
kcf_tools/generate/readme/readme_maker.py
kcf_tools/generate/readme/templates/__init__.py
kcf_tools/generate/readme/templates/readme_template.md
kcf_tools/generate/readme/templates/readme_template.py
kcf_tools/generate/ui_block/__init__.py
kcf_tools/generate/ui_block/main.py
kcf_tools/generate/ui_block/ui_blocks.py
kcf_tools-0.1.5.dist-info/LICENSE
kcf_tools-0.1.5.dist-info/METADATA
kcf_tools-0.1.5.dist-info/WHEEL
kcf_tools-0.1.5.dist-info/entry_points.txt
kcf_tools-0.1.5.dist-info/top_level.txt
kcf_tools-0.1.5.dist-info/RECORD
