Metadata-Version: 2.1
Name: kcf-tools
Version: 0.1.5
Summary: CLI tools for generating documentation and config schemas for Keboola Component development
Home-page: https://github.com/bakobako/kcf-tools
Author: Adam Bako @bakobako
Author-email: adam.bako@keboola.com
Project-URL: Documentation, https://github.com/bakobako/kcf-tools
Classifier: Development Status :: 2 - Pre-Alpha
Classifier: Environment :: Console
Classifier: Intended Audience :: Developers
Classifier: License :: OSI Approved :: MIT License
Classifier: Natural Language :: English
Classifier: Programming Language :: Python :: 3
Classifier: Programming Language :: Python :: 3.7
Requires-Python: >=3.7
License-File: LICENSE
Requires-Dist: click
Requires-Dist: Jinja2 (==3.1.1)
Requires-Dist: prompt-toolkit (==1.0.14)
Requires-Dist: PyInquirer (==1.0.3)
Requires-Dist: Pygments (==2.11.2)
